tinyvdiff/__init__.py
tinyvdiff/constants.py
tinyvdiff/pdf.py
tinyvdiff/pdf2svg.py
tinyvdiff/pytest_plugin.py
tinyvdiff/snapshot.py
tinyvdiff-0.5.0.dist-info/METADATA
tinyvdiff-0.5.0.dist-info/WHEEL
tinyvdiff-0.5.0.dist-info/entry_points.txt
tinyvdiff-0.5.0.dist-info/licenses/LICENSE
tinyvdiff-0.5.0.dist-info/RECORD
