Metadata-Version: 2.4
Name: tinyvdiff
Version: 0.5.0
Summary: Minimalist visual regression testing plugin for pytest
Project-URL: Homepage, https://nanx.me/tinyvdiff/
Project-URL: Documentation, https://nanx.me/tinyvdiff/
Project-URL: Repository, https://github.com/nanxstats/tinyvdiff
Project-URL: Issues, https://github.com/nanxstats/tinyvdiff/issues
Project-URL: Changelog, https://github.com/nanxstats/tinyvdiff/blob/main/CHANGELOG.md
Author-email: Nan Xiao <me@nanx.me>
License-File: LICENSE
Classifier: Development Status :: 3 - Alpha
Classifier: Intended Audience :: Developers
Classifier: License :: OSI Approved :: MIT License
Classifier: Programming Language :: Python :: 3
Classifier: Programming Language :: Python :: 3.10
Classifier: Programming Language :: Python :: 3.11
Classifier: Programming Language :: Python :: 3.12
Classifier: Programming Language :: Python :: 3.13
Classifier: Programming Language :: Python :: 3.14
Classifier: Topic :: Software Development :: Quality Assurance
Classifier: Topic :: Software Development :: Testing
Requires-Python: >=3.10
Requires-Dist: pypdf>=5.1.0
Requires-Dist: pytest>=8.3.3
